marionette/__init__.py
marionette/runtests.py
marionette/chrome/test.xul
marionette/chrome/test2.xul
marionette/chrome/test_anonymous_content.xul
marionette/chrome/test_dialog.xul
marionette/chrome/test_nested_iframe.xul
marionette/runner/test.cert
marionette/runner/test.key
marionette/www/bug814037.html
marionette/www/click_out_of_bounds_overflow.html
marionette/www/clicks.html
marionette/www/cssTransform.html
marionette/www/cssTransform2.html
marionette/www/datetimePage.html
marionette/www/deletingFrame.html
marionette/www/double_click.html
marionette/www/element_bottom.html
marionette/www/element_left.html
marionette/www/element_outside_viewport.html
marionette/www/element_right.html
marionette/www/element_top.html
marionette/www/empty.html
marionette/www/formPage.html
marionette/www/frameset.html
marionette/www/framesetPage2.html
marionette/www/hidden.html
marionette/www/html5Page.html
marionette/www/javascriptPage.html
marionette/www/macbeth.html
marionette/www/modal_dialogs.html
marionette/www/nestedElements.html
marionette/www/rectangles.html
marionette/www/resultPage.html
marionette/www/scroll.html
marionette/www/scroll2.html
marionette/www/scroll3.html
marionette/www/scroll4.html
marionette/www/scroll5.html
marionette/www/shim.js
marionette/www/test.html
marionette/www/testAction.html
marionette/www/testPageSource.html
marionette/www/testPageSource.xml
marionette/www/testPageSourceWithUnicodeChars.html
marionette/www/testSize.html
marionette/www/test_accessibility.html
marionette/www/test_carets_columns.html
marionette/www/test_carets_cursor.html
marionette/www/test_carets_display_none.html
marionette/www/test_carets_iframe.html
marionette/www/test_carets_longtext.html
marionette/www/test_carets_multipleline.html
marionette/www/test_carets_multiplerange.html
marionette/www/test_carets_selection.html
marionette/www/test_clearing.html
marionette/www/test_dynamic.html
marionette/www/test_iframe.html
marionette_client-3.3.0.dist-info/DESCRIPTION.rst
marionette_client-3.3.0.dist-info/METADATA
marionette_client-3.3.0.dist-info/RECORD
marionette_client-3.3.0.dist-info/WHEEL
marionette_client-3.3.0.dist-info/entry_points.txt
marionette_client-3.3.0.dist-info/metadata.json
marionette_client-3.3.0.dist-info/top_level.txt
