Metadata-Version: 2.0
Name: marionette-client
Version: 3.3.0
Summary: Marionette test automation client
Home-page: https://wiki.mozilla.org/Auto-tools/Projects/Marionette
Author: Auto-tools
Author-email: tools-marionette@lists.mozilla.org
License: Mozilla Public License 2.0 (MPL 2.0)
Keywords: mozilla
Platform: UNKNOWN
Classifier: Development Status :: 7 - Inactive
Classifier: Intended Audience :: Developers
Classifier: License :: OSI Approved :: Mozilla Public License 2.0 (MPL 2.0)
Classifier: Operating System :: MacOS :: MacOS X
Classifier: Operating System :: Microsoft :: Windows
Classifier: Operating System :: POSIX
Classifier: Topic :: Software Development :: Quality Assurance
Classifier: Topic :: Software Development :: Testing
Classifier: Topic :: Utilities
Classifier: Programming Language :: Python
Classifier: Programming Language :: Python :: 2.7
Requires-Dist: browsermob-proxy (>=0.6.0)
Requires-Dist: manifestparser (>=1.1)
Requires-Dist: marionette-driver (>=2.2.0)
Requires-Dist: mozcrash (>=0.5)
Requires-Dist: mozdevice (>=0.44)
Requires-Dist: mozinfo (>=0.8)
Requires-Dist: mozlog (>=3.0)
Requires-Dist: moznetwork (>=0.21)
Requires-Dist: mozprocess (>=0.9)
Requires-Dist: mozprofile (>=0.7)
Requires-Dist: mozrunner (>=6.13)
Requires-Dist: moztest (>=0.7)
Requires-Dist: mozversion (>=1.1)
Requires-Dist: wptserve (>=1.3.0)
